alphavantage/__init__.py
alphavantage/alphavantageclient.py
alphavantage/pricehistory/__init__.py
alphavantage/pricehistory/pricehistory.py
alphavantage/pricehistory/pricehistoryitem.py
alphavantage/pricehistory/pricehistorymetadata.py
data/__init__.py
data/redis.py
data/watchlist.py
faith/__init__.py
faith/libs/__init__.py
faith/libs/singleton.py
report/__init__.py
report/accountperformance/__init__.py
report/accountperformance/accountperformance.py
report/accountsummary/__init__.py
report/accountsummary/accountsummary.py
report/currentposition/__init__.py
report/currentposition/currentposition.py
report/optionholding/__init__.py
report/optionholding/optionholding.py
report/optionsellscreener/__init__.py
report/optionsellscreener/optionsellcandidate.py
report/optionsellscreener/optionsellscreener.py
report/symbolhistory/__init__.py
report/symbolhistory/symboldatapackage.py
report/symbolhistory/symbolhistory.py
report/symbolhistory/symbolhistorycontext.py
report/symbolhistory/symbolhistorycontextholding.py
report/symbolhistory/symbolhistorycontextsnapshot.py
report/symbolhistory/symbolhistoryevent.py
robinhood/__init__.py
robinhood/robinhood.py
robinhood/lib/__init__.py
robinhood/lib/errors.py
robinhood/lib/helpers.py
robinhood/lib/robinhoodclient.py
robinhood/lib/account/__init__.py
robinhood/lib/account/account.py
robinhood/lib/account/accountobj.py
robinhood/lib/account/marginbalance.py
robinhood/lib/account/optionevent/__init__.py
robinhood/lib/account/optionevent/optionevent.py
robinhood/lib/account/optionevent/optioneventequitycomponent.py
robinhood/lib/account/optionorder/__init__.py
robinhood/lib/account/optionorder/optionleg.py
robinhood/lib/account/optionorder/optionlegexecution.py
robinhood/lib/account/optionorder/optionorder.py
robinhood/lib/account/optionorder/optionrollingorder.py
robinhood/lib/account/optionposition/__init__.py
robinhood/lib/account/optionposition/optionposition.py
robinhood/lib/account/stockorder/__init__.py
faith-0.0.50.dist-info/LICENSE
faith-0.0.50.dist-info/METADATA
faith-0.0.50.dist-info/WHEEL
faith-0.0.50.dist-info/top_level.txt
faith-0.0.50.dist-info/RECORD
