Metadata-Version: 2.1
Name: faith
Version: 0.0.50
Summary: the faith API for investment portfolio management
Home-page: https://github.com/datability-io/faith
Author: Thomas Wang
Author-email: w@datability.io
License: UNKNOWN
Platform: UNKNOWN
Classifier: Programming Language :: Python :: 3
Classifier: License :: OSI Approved :: MIT License
Classifier: Operating System :: OS Independent
Requires-Dist: asciitree (==0.3.3)
Requires-Dist: pytz (==2019.2)
Requires-Dist: redis (==3.3.8)
Requires-Dist: requests (==2.22.0)
Requires-Dist: termcolor (==1.1.0)
Requires-Dist: terminaltables (==3.1.0)
